ffs_docker_compose/__init__.py
ffs_docker_compose/cli.py
ffs_docker_compose-1.0.0.dist-info/METADATA
ffs_docker_compose-1.0.0.dist-info/WHEEL
ffs_docker_compose-1.0.0.dist-info/entry_points.txt
ffs_docker_compose-1.0.0.dist-info/licenses/LICENSE
ffs_docker_compose-1.0.0.dist-info/RECORD
