Metadata-Version: 2.3
Name: ffs_docker_compose
Version: 1.0.0
Summary: A docker-compose alternative that actually behaves like standalone docker
Project-URL: Homepage, https://github.com/cudy789/ffs-docker-compose
Project-URL: Issues, https://github.com/cudy789/ffs-docker-compose/issues
Author-email: Corey Knutson <corey.knutson789@gmail.com>
License-File: LICENSE
Classifier: License :: OSI Approved :: MIT License
Classifier: Operating System :: OS Independent
Classifier: Programming Language :: Python :: 3
Requires-Python: >=3.5
Requires-Dist: argparse
Requires-Dist: pyyaml
